ssm_mass_uploader/__init__.py
ssm_mass_uploader/__main__.py
ssm_mass_uploader/__version__.py
ssm_mass_uploader/upload_ssm.py
ssm_mass_uploader/aws_utils/__init__.py
ssm_mass_uploader/aws_utils/kms.py
ssm_mass_uploader/aws_utils/ssm.py
ssmu/__init__.py
ssmu/__main__.py
ssmu/__version__.py
ssmu/encrypt_secrets.py
ssmu/upload_ssm.py
ssmu/aws_utils/__init__.py
ssmu/aws_utils/kms.py
ssmu/aws_utils/ssm.py
ssm_mass_uploader-0.1.1.dist-info/LICENSE
ssm_mass_uploader-0.1.1.dist-info/METADATA
ssm_mass_uploader-0.1.1.dist-info/WHEEL
ssm_mass_uploader-0.1.1.dist-info/top_level.txt
ssm_mass_uploader-0.1.1.dist-info/RECORD
