Metadata-Version: 2.1
Name: ssm-mass-uploader
Version: 0.1.1
Summary: pass in a encrypted file and kms key id, the package will decrypt the data, and upload the contents to aws ssm.
Home-page: https://github.com/jayfry1077/ssm_mass_uploader
Author: Jonathan Bradbury
Author-email: jonathanabradbury@gmail.com
License: MIT
Platform: UNKNOWN
Classifier: License :: OSI Approved :: MIT License
Classifier: Programming Language :: Python
Classifier: Programming Language :: Python :: 3
Classifier: Programming Language :: Python :: 3.6
Classifier: Programming Language :: Python :: Implementation :: CPython
Classifier: Programming Language :: Python :: Implementation :: PyPy
Requires-Python: >=3.6.0
Requires-Dist: boto3
